odoo/addons/stock_picking_filter_lot/README.rst
odoo/addons/stock_picking_filter_lot/__init__.py
odoo/addons/stock_picking_filter_lot/__manifest__.py
odoo/addons/stock_picking_filter_lot/i18n/ca.po
odoo/addons/stock_picking_filter_lot/i18n/ca_ES.po
odoo/addons/stock_picking_filter_lot/i18n/it.po
odoo/addons/stock_picking_filter_lot/i18n/stock_picking_filter_lot.pot
odoo/addons/stock_picking_filter_lot/models/__init__.py
odoo/addons/stock_picking_filter_lot/models/stock_move_line.py
odoo/addons/stock_picking_filter_lot/models/stock_picking_type.py
odoo/addons/stock_picking_filter_lot/models/stock_production_lot.py
odoo/addons/stock_picking_filter_lot/readme/CONFIGURATION.rst
odoo/addons/stock_picking_filter_lot/readme/CONTRIBUTORS.rst
odoo/addons/stock_picking_filter_lot/readme/DESCRIPTION.rst
odoo/addons/stock_picking_filter_lot/readme/USAGE.rst
odoo/addons/stock_picking_filter_lot/static/description/icon.png
odoo/addons/stock_picking_filter_lot/static/description/index.html
odoo/addons/stock_picking_filter_lot/views/stock_move_line_view.xml
odoo/addons/stock_picking_filter_lot/views/stock_picking_type_view.xml
odoo/addons/stock_picking_filter_lot/views/stock_scrap_view.xml
odoo14_addon_stock_picking_filter_lot-14.0.2.0.2.dist-info/METADATA
odoo14_addon_stock_picking_filter_lot-14.0.2.0.2.dist-info/WHEEL
odoo14_addon_stock_picking_filter_lot-14.0.2.0.2.dist-info/top_level.txt
odoo14_addon_stock_picking_filter_lot-14.0.2.0.2.dist-info/RECORD
